{"propertiesBar":{"properties":[{"name":"About","expanded":true,"children":[]},{"name":"Colors","expanded":true,"children":[]},{"name":"Startup","expanded":true,"children":[]},{"name":"Display","expanded":true,"children":[{"name":"Viewport size","expanded":false,"children":[]}]},{"name":"Advanced","expanded":true,"children":[]},{"name":"Compatibility settings","expanded":true,"children":[]},{"name":"Editor","expanded":true,"children":[]}],"scrollPosition":0},"openTabs":{"active":{"name":"0-0","type":"layout"},"open":[{"name":"eGame","type":"eventSheet"},{"name":"0-0","type":"layout"},{"name":"0-1","type":"layout"},{"name":"0-2","type":"layout"},{"name":"0-3","type":"layout"},{"name":"0-4","type":"layout"},{"name":"0-5","type":"layout"},{"name":"0-6","type":"layout"},{"name":"0-7","type":"layout"},{"name":"1-1","type":"layout"},{"name":"1-2","type":"layout"},{"name":"1-3","type":"layout"},{"name":"e1-3","type":"eventSheet"},{"name":"Real Win","type":"layout"},{"name":"Win!","type":"layout"},{"name":"Rip","type":"layout"},{"name":"1-4","type":"layout"},{"name":"eIntro","type":"eventSheet"},{"name":"e1-1","type":"eventSheet"},{"name":"e1-2","type":"eventSheet"}]},"previewEffects":true,"previewBrowser":"default","pauseOnUnfocus":false,"projectBar":{"name":"<root>","children":[{"name":"Dont Melt","expanded":true,"children":[{"name":"Layouts","expanded":true,"children":[{"name":"Levels","expanded":true,"children":[{"name":"World 0","expanded":true,"children":[{"name":"0-0","expanded":true,"children":[]},{"name":"0-1","expanded":true,"children":[]},{"name":"0-2","expanded":true,"children":[]},{"name":"0-3","expanded":true,"children":[]},{"name":"0-4","expanded":true,"children":[]},{"name":"0-5","expanded":true,"children":[]},{"name":"0-6","expanded":true,"children":[]},{"name":"0-7","expanded":true,"children":[]},{"name":"Win!","expanded":true,"children":[]}]},{"name":"World 1","expanded":true,"children":[{"name":"1-1","expanded":true,"children":[]},{"name":"1-2","expanded":true,"children":[]},{"name":"1-3","expanded":true,"children":[]},{"name":"Real Win","expanded":true,"children":[]},{"name":"1-4","expanded":true,"children":[]},{"name":"1-5","expanded":true,"children":[]}]}]},{"name":"Intro","expanded":true,"children":[]},{"name":"Rip","expanded":true,"children":[]}]},{"name":"Event sheets","expanded":true,"children":[{"name":"Levels","expanded":true,"children":[{"name":"e0-3","expanded":true,"children":[]},{"name":"e1-1","expanded":true,"children":[]},{"name":"e1-2","expanded":true,"children":[]},{"name":"e1-3","expanded":true,"children":[]}]},{"name":"eGame","expanded":true,"children":[]},{"name":"eIntro","expanded":true,"children":[]}]},{"name":"Scripts","expanded":true,"children":[]},{"name":"Object types","expanded":true,"children":[{"name":"Backgrounds & Overlays & Textures","expanded":true,"children":[{"name":"Backgrounds","expanded":true,"children":[{"name":"CardboardBackground","expanded":true,"children":[]},{"name":"PaperBackground","expanded":true,"children":[]}]},{"name":"Overlays","expanded":true,"children":[{"name":"Glitter","expanded":true,"children":[]},{"name":"GlitterNormal","expanded":true,"children":[]},{"name":"Tape","expanded":true,"children":[]}]},{"name":"Textures","expanded":true,"children":[{"name":"CardboardFrontTexture","expanded":true,"children":[]},{"name":"CardboardSideTexture","expanded":true,"children":[]},{"name":"CardboardTexture","expanded":true,"children":[]},{"name":"Newspaper","expanded":true,"children":[]},{"name":"Snow","expanded":true,"children":[]}]}]},{"name":"FX","expanded":true,"children":[{"name":"Confetti","expanded":true,"children":[]},{"name":"ConfettiParticles","expanded":true,"children":[]},{"name":"Mist","expanded":true,"children":[]},{"name":"ParticlesBig","expanded":true,"children":[]},{"name":"ParticlesMid","expanded":true,"children":[]},{"name":"snowBall","expanded":true,"children":[]},{"name":"snowBallParticles","expanded":true,"children":[]},{"name":"StarParticles","expanded":true,"children":[]},{"name":"StarWarp","expanded":true,"children":[]},{"name":"ZMist","expanded":true,"children":[]}]},{"name":"Gizmos","expanded":true,"children":[{"name":"CameraLock","expanded":true,"children":[]},{"name":"CollisionTrigger","expanded":true,"children":[]},{"name":"InvisibleMask","expanded":true,"children":[]},{"name":"LayoutManager","expanded":true,"children":[]},{"name":"PhysicsAnchor","expanded":true,"children":[]},{"name":"PhysicsObject","expanded":true,"children":[]},{"name":"SimpleSlope","expanded":true,"children":[]},{"name":"slope","expanded":true,"children":[]}]},{"name":"Intro","expanded":false,"children":[{"name":"Construct3","expanded":true,"children":[]}]},{"name":"Objects","expanded":true,"children":[{"name":"Hints","expanded":true,"children":[{"name":"heatLampLabel","expanded":true,"children":[]},{"name":"hint0","expanded":true,"children":[]},{"name":"hint1","expanded":true,"children":[]},{"name":"hint2","expanded":true,"children":[]}]},{"name":"BreakableFloor","expanded":true,"children":[]},{"name":"BreakableWall","expanded":true,"children":[]},{"name":"catArm","expanded":true,"children":[]},{"name":"Character","expanded":true,"children":[]},{"name":"CottonBalls","expanded":true,"children":[]},{"name":"Cupbottom","expanded":true,"children":[]},{"name":"Cuptop","expanded":true,"children":[]},{"name":"Dice","expanded":true,"children":[]},{"name":"Fan","expanded":true,"children":[]},{"name":"FanLift","expanded":true,"children":[]},{"name":"fire","expanded":true,"children":[]},{"name":"froster","expanded":true,"children":[]},{"name":"FrosterCollision","expanded":true,"children":[]},{"name":"Ground","expanded":true,"children":[]},{"name":"Heat","expanded":true,"children":[]},{"name":"IndependentFloor","expanded":true,"children":[]},{"name":"IndependentSlope","expanded":true,"children":[]},{"name":"IndependentWall","expanded":true,"children":[]},{"name":"JumpThroughGround","expanded":true,"children":[]},{"name":"MovingGround","expanded":true,"children":[]},{"name":"MovingPlatform","expanded":true,"children":[]},{"name":"MovingPlatform3D","expanded":true,"children":[]},{"name":"Player","expanded":true,"children":[]},{"name":"PlayerClickbox","expanded":true,"children":[]},{"name":"Pushable","expanded":true,"children":[]},{"name":"RedButton","expanded":true,"children":[]},{"name":"redLight","expanded":true,"children":[]},{"name":"Rope","expanded":true,"children":[]},{"name":"Star","expanded":true,"children":[]},{"name":"StopSpring","expanded":true,"children":[]},{"name":"Streamer","expanded":true,"children":[]},{"name":"StreamerPoint","expanded":true,"children":[]},{"name":"StrongSpring","expanded":true,"children":[]},{"name":"TheChillZone","expanded":true,"children":[]},{"name":"Tilemap","expanded":true,"children":[]},{"name":"Umbrella","expanded":true,"children":[]},{"name":"WallSpring","expanded":true,"children":[]},{"name":"WeakSpring","expanded":true,"children":[]}]},{"name":"UI","expanded":true,"children":[{"name":"ball","expanded":true,"children":[]},{"name":"BallTrack","expanded":true,"children":[]},{"name":"Cursor","expanded":true,"children":[]},{"name":"DeathCount","expanded":true,"children":[]},{"name":"DeathDarkness","expanded":true,"children":[]},{"name":"DeathIcon","expanded":true,"children":[]},{"name":"DontMelt","expanded":true,"children":[]},{"name":"EndText","expanded":true,"children":[]},{"name":"forRealNow","expanded":true,"children":[]},{"name":"goBack","expanded":true,"children":[]},{"name":"Instagram","expanded":true,"children":[]},{"name":"MeltMeter","expanded":true,"children":[]},{"name":"No","expanded":true,"children":[]},{"name":"noBlue","expanded":true,"children":[]},{"name":"NoNudge","expanded":true,"children":[]},{"name":"Or","expanded":true,"children":[]},{"name":"Reset","expanded":true,"children":[]},{"name":"resetLevel","expanded":true,"children":[]},{"name":"saveMyPc","expanded":true,"children":[]},{"name":"saveMyPcTrack","expanded":true,"children":[]},{"name":"Soundcloud","expanded":true,"children":[]},{"name":"StarCount","expanded":true,"children":[]},{"name":"StarCount2","expanded":true,"children":[]},{"name":"StarIcon","expanded":true,"children":[]},{"name":"ThankYou","expanded":true,"children":[]},{"name":"USure","expanded":true,"children":[]},{"name":"USureBlue","expanded":true,"children":[]},{"name":"WarningText","expanded":true,"children":[]},{"name":"Yea","expanded":true,"children":[]},{"name":"yesBlue","expanded":true,"children":[]}]},{"name":"AJAX","expanded":true,"children":[]},{"name":"Audio","expanded":true,"children":[]},{"name":"Browser","expanded":true,"children":[]},{"name":"FileSystem","expanded":true,"children":[]},{"name":"JSON","expanded":true,"children":[]},{"name":"Keyboard","expanded":true,"children":[]},{"name":"LocalStorage","expanded":true,"children":[]},{"name":"Mouse","expanded":true,"children":[]},{"name":"Tick","expanded":true,"children":[]},{"name":"TimelineController","expanded":true,"children":[]},{"name":"Utils","expanded":true,"children":[]}]},{"name":"Families","expanded":true,"children":[{"name":"Breakable","expanded":false,"children":[{"name":"BreakableFloor","expanded":true,"children":[]},{"name":"BreakableWall","expanded":true,"children":[]}]},{"name":"Clickables","expanded":false,"children":[{"name":"ball","expanded":true,"children":[]},{"name":"BreakableFloor","expanded":true,"children":[]},{"name":"BreakableWall","expanded":true,"children":[]},{"name":"goBack","expanded":true,"children":[]},{"name":"No","expanded":true,"children":[]},{"name":"noBlue","expanded":true,"children":[]},{"name":"PlayerClickbox","expanded":true,"children":[]},{"name":"RedButton","expanded":true,"children":[]},{"name":"redLight","expanded":true,"children":[]},{"name":"Reset","expanded":true,"children":[]},{"name":"resetLevel","expanded":true,"children":[]},{"name":"saveMyPc","expanded":true,"children":[]},{"name":"saveMyPcTrack","expanded":true,"children":[]},{"name":"Star","expanded":true,"children":[]},{"name":"USure","expanded":true,"children":[]},{"name":"USureBlue","expanded":true,"children":[]},{"name":"Yea","expanded":true,"children":[]},{"name":"yesBlue","expanded":true,"children":[]}]},{"name":"UIbuttons","expanded":false,"children":[{"name":"goBack","expanded":true,"children":[]},{"name":"No","expanded":true,"children":[]},{"name":"noBlue","expanded":true,"children":[]},{"name":"Reset","expanded":true,"children":[]},{"name":"resetLevel","expanded":true,"children":[]},{"name":"Yea","expanded":true,"children":[]},{"name":"yesBlue","expanded":true,"children":[]}]}]},{"name":"Timelines","expanded":false,"children":[{"name":"Eases","expanded":false,"children":[]},{"name":"Cat","expanded":true,"children":[]}]},{"name":"Flowcharts","expanded":true,"children":[]},{"name":"Sounds","expanded":true,"children":[{"name":"break.webm","expanded":true,"children":[]},{"name":"cat.webm","expanded":true,"children":[]},{"name":"click.webm","expanded":true,"children":[]},{"name":"click2.webm","expanded":true,"children":[]},{"name":"damage.webm","expanded":true,"children":[]},{"name":"die.webm","expanded":true,"children":[]},{"name":"fastRelease.webm","expanded":true,"children":[]},{"name":"grab.webm","expanded":true,"children":[]},{"name":"hitHurt.webm","expanded":true,"children":[]},{"name":"jump.webm","expanded":true,"children":[]},{"name":"land.webm","expanded":true,"children":[]},{"name":"lightSwitch.webm","expanded":true,"children":[]},{"name":"newStar.webm","expanded":true,"children":[]},{"name":"pickupCoin.webm","expanded":true,"children":[]},{"name":"powerUp.webm","expanded":true,"children":[]},{"name":"show.webm","expanded":true,"children":[]}]},{"name":"Music","expanded":true,"children":[{"name":"theme 2.webm","expanded":true,"children":[]},{"name":"theme.webm","expanded":true,"children":[]},{"name":"win 2.webm","expanded":true,"children":[]},{"name":"win 3.webm","expanded":true,"children":[]},{"name":"win.webm","expanded":true,"children":[]}]},{"name":"Videos","expanded":true,"children":[]},{"name":"Fonts","expanded":true,"children":[]},{"name":"Icons & screenshots","expanded":false,"children":[{"name":"icon-128.png","expanded":true,"children":[]},{"name":"icon-16.png","expanded":true,"children":[]},{"name":"icon-256.png","expanded":true,"children":[]},{"name":"icon-32.png","expanded":true,"children":[]},{"name":"icon-512.png","expanded":true,"children":[]},{"name":"icon-64.png","expanded":true,"children":[]},{"name":"loading-logo.png","expanded":true,"children":[]}]},{"name":"Files","expanded":true,"children":[{"name":"blank-save-data.json","expanded":true,"children":[]},{"name":"c3logo-lightbg.svg","expanded":true,"children":[]}]}]}]},"propertiesBarActiveObject":{"name":"0-0","type":"layout"},"containers":[{"selectMode":"normal"},{"selectMode":"normal"}]}